{
  "last_sync_at": "2026-04-07T12:11:06.796Z",
  "last_core_version": "2.6.31",
  "imported_la_ids": [
    "LA-CORE-001",
    "LA-CORE-002",
    "LA-CORE-003",
    "LA-CORE-004",
    "LA-CORE-005",
    "LA-CORE-006",
    "LA-CORE-007",
    "LA-CORE-008",
    "LA-CORE-009",
    "LA-CORE-010",
    "LA-CORE-011",
    "LA-CORE-012",
    "LA-CORE-013",
    "LA-CORE-014",
    "LA-CORE-015",
    "LA-CORE-016",
    "LA-CORE-017",
    "LA-CORE-018",
    "LA-CORE-019",
    "LA-CORE-020",
    "LA-CORE-021",
    "LA-CORE-022",
    "LA-CORE-023",
    "LA-CORE-024",
    "LA-CORE-025",
    "LA-CORE-026",
    "LA-CORE-027",
    "LA-CORE-028",
    "LA-CORE-029",
    "LA-CORE-030",
    "LA-CORE-031",
    "LA-CORE-032",
    "LA-023-01",
    "LA-CORE-033"
  ],
  "skipped_la_ids": [],
  "sync_history": [
    {
      "synced_at": "2026-04-07T12:04:57.162Z",
      "core_version": "2.6.29",
      "new_las": [
        "LA-CORE-001",
        "LA-CORE-002",
        "LA-CORE-003",
        "LA-CORE-004",
        "LA-CORE-005",
        "LA-CORE-006",
        "LA-CORE-007",
        "LA-CORE-008",
        "LA-CORE-009",
        "LA-CORE-010",
        "LA-CORE-011",
        "LA-CORE-012",
        "LA-CORE-013",
        "LA-CORE-014",
        "LA-CORE-015",
        "LA-CORE-016",
        "LA-CORE-017",
        "LA-CORE-018",
        "LA-CORE-019",
        "LA-CORE-020",
        "LA-CORE-021",
        "LA-CORE-022",
        "LA-CORE-023",
        "LA-CORE-024",
        "LA-CORE-025",
        "LA-CORE-026",
        "LA-CORE-027",
        "LA-CORE-028",
        "LA-CORE-029",
        "LA-CORE-030",
        "LA-CORE-031",
        "LA-CORE-032",
        "LA-023-01"
      ],
      "skills_updated": [],
      "mode": "delta"
    },
    {
      "synced_at": "2026-04-07T12:11:06.796Z",
      "core_version": "2.6.31",
      "new_las": [
        "LA-CORE-033"
      ],
      "skills_updated": [],
      "mode": "delta"
    }
  ]
}